django_essentials_kit/__init__.py
django_essentials_kit/admin.py
django_essentials_kit/logger_formatter.py
django_essentials_kit/middlewares.py
django_essentials_kit/utils.py
django_essentials_kit/management/__init__.py
django_essentials_kit/management/commands/__init__.py
django_essentials_kit/management/commands/create_super_user.py
django_essentials_kit/rest_framework/__init__.py
django_essentials_kit/rest_framework/parsers.py
django_essentials_kit/rest_framework/views.py
django_essentials_kit-0.1.6.dist-info/licenses/LICENSE
django_essentials_kit-0.1.6.dist-info/METADATA
django_essentials_kit-0.1.6.dist-info/WHEEL
django_essentials_kit-0.1.6.dist-info/top_level.txt
django_essentials_kit-0.1.6.dist-info/RECORD
