Metadata-Version: 2.4
Name: django-essentials-kit
Version: 0.1.6
Summary: Essential utilities for Django
Home-page: https://github.com/alex-deus/django-essentials-kit
Author: Alex Deus
License: MIT
Project-URL: Homepage, https://github.com/alex-deus/django-essentials-kit
Project-URL: Repository, https://github.com/alex-deus/django-essentials-kit
Project-URL: Issues, https://github.com/alex-deus/django-essentials-kit/issues
Keywords: django,utilities,django-admin
Classifier: Development Status :: 3 - Alpha
Classifier: Intended Audience :: Developers
Classifier: License :: OSI Approved :: MIT License
Classifier: Operating System :: OS Independent
Classifier: Programming Language :: Python :: 3
Classifier: Programming Language :: Python :: 3.8
Classifier: Programming Language :: Python :: 3.9
Classifier: Programming Language :: Python :: 3.10
Classifier: Programming Language :: Python :: 3.11
Classifier: Programming Language :: Python :: 3.12
Classifier: Framework :: Django
Classifier: Framework :: Django :: 3.2
Classifier: Framework :: Django :: 4.0
Classifier: Framework :: Django :: 4.1
Classifier: Framework :: Django :: 4.2
Classifier: Framework :: Django :: 5.0
Requires-Python: >=3.8
License-File: LICENSE
Requires-Dist: Django>=3.2
Requires-Dist: json-log-formatter<2.0.0,>=1.1.1
Requires-Dist: django-ipware<8.0.0,>=7.0.1
Dynamic: home-page
Dynamic: license-file
Dynamic: requires-python
